riscv_matmul/riscv_matmul.srcs/sources_1/new/alu_control.v
`timescale 1ns / 1ps

module alu_control(
  input      [2 : 0] funct3,
  input      [6 : 0] funct7,
  input      [1 : 0] alu_op,
  
  output reg [3 : 0] alu_control_out
);

  always @ (*) begin
    case ({alu_op, funct7, funct3})
    12'b10_0000000_000 : alu_control_out <= 4'b0000; // ADD 
    12'b00_0000000_000 : alu_control_out <= 4'b0000; // ADD 
    12'b00_0000000_001 : alu_control_out <= 4'b0000; // ADD 
    12'b00_0000000_010 : alu_control_out <= 4'b0000; // ADD 
    12'b10_0100000_000 : alu_control_out <= 4'b0001; // SUB 
    12'b10_0000000_111 : alu_control_out <= 4'b0010; // AND
    12'b10_0000000_110 : alu_control_out <= 4'b0011; // OR
    12'b10_0000000_100 : alu_control_out <= 4'b0100; // XOR
    12'b10_0000000_001 : alu_control_out <= 4'b0101; // SLL
    12'b10_0000000_101 : alu_control_out <= 4'b0110; // SRL
    12'b10_0100000_101 : alu_control_out <= 4'b0111; // SRA
    12'b10_0000000_010 : alu_control_out <= 4'b1000; // SLT
    default            : alu_control_out <= 4'b0000; 
    endcase
  end

endmodule

riscv_matmul/riscv_matmul.srcs/sim_1/new/tb_alu_control.sv
`timescale 1ns / 1ps

module tb_alu_control();
  
  // Testbench signals
  reg [2:0] funct3;
  reg [6:0] funct7;
  reg [1:0] alu_op;
  wire [3:0] alu_control_out;
  
  // Expected output storage
  reg [3:0] exp_alu_control_out;
  
  // Test control
  integer test_count = 0;
  integer pass_count = 0;
  integer fail_count = 0;
  reg test_pass;
  
  // Instruction names for reporting
  string instruction_name;
  
  // Instantiate the module under test
  alu_control dut (
    .funct3(funct3),
    .funct7(funct7),
    .alu_op(alu_op),
    .alu_control_out(alu_control_out)
  );
  
  // Task to check outputs against expected values
  task check_outputs;
    input [1:0] alu_op_input;
    input [6:0] funct7_input;
    input [2:0] funct3_input;
    input [3:0] exp_alu_ctrl;
    input string instr_name;
    
    begin
      test_count = test_count + 1;
      test_pass = 1;
      
      // Apply inputs
      alu_op = alu_op_input;
      funct7 = funct7_input;
      funct3 = funct3_input;
      instruction_name = instr_name;
      
      #10; // Wait for combinational logic to settle
      
      // Check output
      if (alu_control_out !== exp_alu_ctrl) begin
        $display("FAIL: %s", instruction_name);
        $display("  Inputs: alu_op=%b, funct7=%b, funct3=%b", 
                 alu_op_input, funct7_input, funct3_input);
        $display("  Expected: %b (decimal %0d)", exp_alu_ctrl, exp_alu_ctrl);
        $display("  Got:      %b (decimal %0d)", alu_control_out, alu_control_out);
        test_pass = 0;
      end
      
      if (test_pass) begin
        $display("PASS: %s", instruction_name);
        pass_count = pass_count + 1;
      end else begin
        fail_count = fail_count + 1;
      end
    end
  endtask
  
  // Initialize test
  initial begin
    $display("=================================");
    $display("Starting testbench for alu_control");
    $display("=================================\n");
    
    // Group tests by ALU operation type
    $display("=== R-Type Instructions (alu_op = 2'b10) ===");
    
    // Test 1: ADD instruction
    check_outputs(2'b10, 7'b0000000, 3'b000, 4'b0000, "ADD");
    
    // Test 2: SUB instruction
    check_outputs(2'b10, 7'b0100000, 3'b000, 4'b0001, "SUB");
    
    // Test 3: AND instruction
    check_outputs(2'b10, 7'b0000000, 3'b111, 4'b0010, "AND");
    
    // Test 4: OR instruction
    check_outputs(2'b10, 7'b0000000, 3'b110, 4'b0011, "OR");
    
    // Test 5: XOR instruction
    check_outputs(2'b10, 7'b0000000, 3'b100, 4'b0100, "XOR");
    
    // Test 6: SLL (Shift Left Logical) instruction
    check_outputs(2'b10, 7'b0000000, 3'b001, 4'b0101, "SLL");
    
    // Test 7: SRL (Shift Right Logical) instruction
    check_outputs(2'b10, 7'b0000000, 3'b101, 4'b0110, "SRL");
    
    // Test 8: SRA (Shift Right Arithmetic) instruction
    check_outputs(2'b10, 7'b0100000, 3'b101, 4'b0111, "SRA");
    
    // Test 9: SLT (Set Less Than) instruction
    check_outputs(2'b10, 7'b0000000, 3'b010, 4'b1000, "SLT");
    
    // Test additional R-type variations
    $display("\n=== Additional R-Type Tests ===");
    check_outputs(2'b10, 7'b0000000, 3'b011, 4'b0000, "R-type with funct3=011 (defaults to ADD)");
    check_outputs(2'b10, 7'b1111111, 3'b000, 4'b0000, "R-type with funct7=1111111 (defaults to ADD)");
    
    $display("\n=== Load/Store Instructions (alu_op = 2'b00) ===");
    // Test load/store operations - should all be ADD for address calculation
    check_outputs(2'b00, 7'b0000000, 3'b000, 4'b0000, "Load (LB/LH/LW/LBU/LHU) - funct3=000");
    check_outputs(2'b00, 7'b0000000, 3'b001, 4'b0000, "Load (LH) - funct3=001");
    check_outputs(2'b00, 7'b0000000, 3'b010, 4'b0000, "Load (LW) - funct3=010");
    check_outputs(2'b00, 7'b0000000, 3'b011, 4'b0000, "Load (funct3=011 defaults to ADD)");
    check_outputs(2'b00, 7'b0000000, 3'b100, 4'b0000, "Load (LBU) - funct3=100");
    check_outputs(2'b00, 7'b0000000, 3'b101, 4'b0000, "Load (LHU) - funct3=101");
    check_outputs(2'b00, 7'b1111111, 3'b010, 4'b0000, "Store (SW) with funct7=1111111 (still ADD)");
    
    $display("\n=== I-Type Immediate Instructions (should use alu_op=2'b10) ===");
    // Note: I-type instructions use the same ALU control as R-type
    check_outputs(2'b10, 7'b0000000, 3'b000, 4'b0000, "ADDI");
    check_outputs(2'b10, 7'b0000000, 3'b111, 4'b0010, "ANDI");
    check_outputs(2'b10, 7'b0000000, 3'b110, 4'b0011, "ORI");
    check_outputs(2'b10, 7'b0000000, 3'b100, 4'b0100, "XORI");
    check_outputs(2'b10, 7'b0000000, 3'b001, 4'b0101, "SLLI");
    check_outputs(2'b10, 7'b0000000, 3'b101, 4'b0110, "SRLI");
    check_outputs(2'b10, 7'b0100000, 3'b101, 4'b0111, "SRAI");
    check_outputs(2'b10, 7'b0000000, 3'b010, 4'b1000, "SLTI");
    
    $display("\n=== Undefined/Default Cases ===");
    // Test undefined alu_op values
    check_outputs(2'b01, 7'b0000000, 3'b000, 4'b0000, "Undefined alu_op=01 (defaults to ADD)");
    check_outputs(2'b11, 7'b0000000, 3'b000, 4'b0000, "Undefined alu_op=11 (defaults to ADD)");
    
    // Test undefined combinations
    check_outputs(2'b10, 7'b0010000, 3'b000, 4'b0000, "Undefined funct7=0010000 (defaults to ADD)");
    check_outputs(2'b10, 7'b0000000, 3'b111, 4'b0010, "AND (re-test to ensure no interference)");
    
    $display("\n=== Edge Cases and Stress Testing ===");
    // Random testing
    for (integer i = 0; i < 10; i = i + 1) begin
      reg [1:0] rand_alu_op = $random;
      reg [6:0] rand_funct7 = $random;
      reg [2:0] rand_funct3 = $random;
      
      alu_op = rand_alu_op;
      funct7 = rand_funct7;
      funct3 = rand_funct3;
      
      #5;
      // Just observe behavior, no explicit check for random values
    end
    
    // Test all possible funct3 values for each alu_op
    $display("\n=== Exhaustive funct3 Testing ===");
    for (integer f3 = 0; f3 < 8; f3 = f3 + 1) begin
      alu_op = 2'b00;
      funct7 = 7'b0000000;
      funct3 = f3;
      #5;
      $display("alu_op=00, funct3=%3b -> alu_ctrl=%b", f3, alu_control_out);
    end
    
    // Final summary
    $display("\n=================================");
    $display("Test Summary");
    $display("=================================");
    $display("Total tests run: %0d", test_count);
    $display("Tests passed:    %0d", pass_count);
    $display("Tests failed:    %0d", fail_count);
    
    if (fail_count == 0) begin
      $display("\n✅ ALL TESTS PASSED!");
    end else begin
      $display("\n❌ SOME TESTS FAILED!");
    end
    
    $display("=================================\n");
    
    // Display ALU control code mapping
    $display("ALU Control Code Mapping:");
    $display("  0000: ADD");
    $display("  0001: SUB");
    $display("  0010: AND");
    $display("  0011: OR");
    $display("  0100: XOR");
    $display("  0101: SLL");
    $display("  0110: SRL");
    $display("  0111: SRA");
    $display("  1000: SLT");
    $display("  Default: ADD (0000)");
    
    // End simulation
    #10;
    $finish;
  end
  
  // Monitor to track signal changes
  initial begin
    // Only display changes during the main test phase
    wait(test_count > 0);
    $monitor("Time: %0t | alu_op=%b, funct7=%b, funct3=%b -> alu_ctrl=%b", 
             $time, alu_op, funct7, funct3, alu_control_out);
  end
  
  // Generate waveform dump
  initial begin
    $dumpfile("alu_control.vcd");
    $dumpvars(0, tb_alu_control);
  end
  
  // Helper function to decode ALU control signal
  function string decode_alu_ctrl(input [3:0] ctrl);
    begin
      case (ctrl)
        4'b0000: decode_alu_ctrl = "ADD";
        4'b0001: decode_alu_ctrl = "SUB";
        4'b0010: decode_alu_ctrl = "AND";
        4'b0011: decode_alu_ctrl = "OR";
        4'b0100: decode_alu_ctrl = "XOR";
        4'b0101: decode_alu_ctrl = "SLL";
        4'b0110: decode_alu_ctrl = "SRL";
        4'b0111: decode_alu_ctrl = "SRA";
        4'b1000: decode_alu_ctrl = "SLT";
        default: decode_alu_ctrl = "UNKNOWN";
      endcase
    end
  endfunction
  
endmodule

riscv_matmul/riscv_matmul.sim/sim_1/behav/xsim/alu_control.vcd
$date
   Mon Dec 29 23:38:23 2025
$end

$version
  2023.2
  $dumpfile ("alu_control.vcd") 
$end

$timescale
  1ps
$end

$scope module tb_alu_control $end
$var reg 3 ! funct3 [2:0] $end
$var reg 7 " funct7 [6:0] $end
$var reg 2 # alu_op [1:0] $end
$var wire 4 $ alu_control_out [3:0] $end
$var reg 4 % exp_alu_control_out [3:0] $end
$var integer 32 & test_count [31:0] $end
$var integer 32 ' pass_count [31:0] $end
$var integer 32 ( fail_count [31:0] $end
$var reg 1 ) test_pass $end
$scope module dut $end
$var wire 3 * funct3 [2:0] $end
$var wire 7 + funct7 [6:0] $end
$var wire 2 , alu_op [1:0] $end
$var reg 4 - alu_control_out [3:0] $end
$upscope $end
$scope begin Block143_2 $end
$var integer 32 . i [31:0] $end
$scope begin Block143_3 $end
$var reg 2 / rand_alu_op [1:0] $end
$var reg 7 0 rand_funct7 [6:0] $end
$var reg 3 1 rand_funct3 [2:0] $end
$upscope $end
$upscope $end
$scope begin Block158_4 $end
$var integer 32 2 f3 [31:0] $end
$upscope $end
$scope task check_outputs $end
$var reg 2 3 alu_op_input [1:0] $end
$var reg 7 4 funct7_input [6:0] $end
$var reg 3 5 funct3_input [2:0] $end
$var reg 4 6 exp_alu_ctrl [3:0] $end
$upscope $end
$upscope $end
$enddefinitions $end

#0
$dumpvars
b0 !
b0 "
b10 #
b0 $
bx %
b1 &
b0 '
b0 (
1)
b0 *
b0 +
b10 ,
b0 -
bx .
bx /
bx 0
bx 1
bx 2
b10 3
b0 4
b0 5
b0 6
$end

#10000
b100000 "
b1 $
b10 &
b1 '
b100000 +
b1 -
b100000 4
b1 6

#20000
b111 !
b0 "
b10 $
b11 &
b10 '
b111 *
b0 +
b10 -
b0 4
b111 5
b10 6

#30000
b110 !
b11 $
b100 &
b11 '
b110 *
b11 -
b110 5
b11 6

#40000
b100 !
b100 $
b101 &
b100 '
b100 *
b100 -
b100 5
b100 6

#50000
b1 !
b101 $
b110 &
b101 '
b1 *
b101 -
b1 5
b101 6

#60000
b101 !
b110 $
b111 &
b110 '
b101 *
b110 -
b101 5
b110 6

#70000
b100000 "
b111 $
b1000 &
b111 '
b100000 +
b111 -
b100000 4
b111 6

#80000
b10 !
b0 "
b1000 $
b1001 &
b1000 '
b10 *
b0 +
b1000 -
b0 4
b10 5
b1000 6

#90000
b11 !
b0 $
b1010 &
b1001 '
b11 *
b0 -
b11 5
b0 6

#100000
b0 !
b1111111 "
b1011 &
b1010 '
b0 *
b1111111 +
b1111111 4
b0 5

#110000
b0 "
b0 #
b1100 &
b1011 '
b0 +
b0 ,
b0 3
b0 4

#120000
b1 !
b1101 &
b1100 '
b1 *
b1 5

#130000
b10 !
b1110 &
b1101 '
b10 *
b10 5

#140000
b11 !
b1111 &
b1110 '
b11 *
b11 5

#150000
b100 !
b10000 &
b1111 '
b100 *
b100 5

#160000
b101 !
b10001 &
b10000 '
b101 *
b101 5

#170000
b10 !
b1111111 "
b10010 &
b10001 '
b10 *
b1111111 +
b1111111 4
b10 5

#180000
b0 !
b0 "
b10 #
b10011 &
b10010 '
b0 *
b0 +
b10 ,
b10 3
b0 4
b0 5

#190000
b111 !
b10 $
b10100 &
b10011 '
b111 *
b10 -
b111 5
b10 6

#200000
b110 !
b11 $
b10101 &
b10100 '
b110 *
b11 -
b110 5
b11 6

#210000
b100 !
b100 $
b10110 &
b10101 '
b100 *
b100 -
b100 5
b100 6

#220000
b1 !
b101 $
b10111 &
b10110 '
b1 *
b101 -
b1 5
b101 6

#230000
b101 !
b110 $
b11000 &
b10111 '
b101 *
b110 -
b101 5
b110 6

#240000
b100000 "
b111 $
b11001 &
b11000 '
b100000 +
b111 -
b100000 4
b111 6

#250000
b10 !
b0 "
b1000 $
b11010 &
b11001 '
b10 *
b0 +
b1000 -
b0 4
b10 5
b1000 6

#260000
b0 !
b1 #
b0 $
b11011 &
b11010 '
b0 *
b1 ,
b0 -
b1 3
b0 5
b0 6

#270000
b11 #
b11100 &
b11011 '
b11 ,
b11 3

#280000
b10000 "
b10 #
b11101 &
b11100 '
b10000 +
b10 ,
b10 3
b10000 4

#290000
b111 !
b0 "
b10 $
b11110 &
b11101 '
b111 *
b0 +
b10 -
b0 4
b111 5
b10 6

#300000
b1 !
b1 "
b0 #
b0 $
b11110 '
b1 *
b1 +
b0 ,
b0 -
b0 .
b0 /
b1 0
b1 1

#305000
b101 !
b1101 "
b11 #
b101 *
b1101 +
b11 ,
b1 .
b11 /
b1101 0
b101 1

#310000
b1 !
b10010 "
b1 #
b1 *
b10010 +
b1 ,
b10 .
b1 /
b10010 0
b1 1

#315000
b101 !
b1110110 "
b101 *
b1110110 +
b11 .
b1110110 0
b101 1

#320000
b1 !
b1100 "
b1 *
b1100 +
b100 .
b1100 0
b1 1

#325000
b10 !
b1000101 "
b10 #
b10 *
b1000101 +
b10 ,
b101 .
b10 /
b1000101 0
b10 1

#330000
b1110111 "
b1 #
b1110111 +
b1 ,
b110 .
b1 /
b1110111 0

#335000
b110 !
b1110010 "
b11 #
b110 *
b1110010 +
b11 ,
b111 .
b11 /
b1110010 0
b110 1

#340000
b100 !
b1000101 "
b0 #
b100 *
b1000101 +
b0 ,
b1000 .
b0 /
b1000101 0
b100 1

#345000
b101 !
b101101 "
b1 #
b101 *
b101101 +
b1 ,
b1001 .
b1 /
b101101 0
b101 1

#350000
b0 !
b0 "
b0 #
b0 *
b0 +
b0 ,
b1010 .
b0 2

#355000
b1 !
b1 *
b1 2

#360000
b10 !
b10 *
b10 2

#365000
b11 !
b11 *
b11 2

#370000
b100 !
b100 *
b100 2

#375000
b101 !
b101 *
b101 2

#380000
b110 !
b110 *
b110 2

#385000
b111 !
b111 *
b111 2

#390000
b1000 2
