riscv_matmul/riscv_matmul.srcs/sources_1/new/main_control_unit.v
`timescale 1ns / 1ps

module main_control_unit(
  input      [6 : 0] opcode,
  
  output reg         regwrite,
  output reg         memread,
  output reg         memwrite,
  output reg         memtoreg,
  output reg         alusrc,
  output reg         branch,
  output reg [1 : 0] aluop
);

  always @ (*) begin
    case (opcode) 
      7'b0110011 : {alusrc, memtoreg, regwrite, memread, memwrite, branch, aluop} <= {1'b0, 1'b0, 1'b1, 1'b0, 1'b0, 1'b0, 2'b10}; // R-type
      7'b0010011 : {alusrc, memtoreg, regwrite, memread, memwrite, branch, aluop} <= {1'b1, 1'b0, 1'b1, 1'b0, 1'b0, 1'b0, 2'b10}; // I-type
      7'b0000011 : {alusrc, memtoreg, regwrite, memread, memwrite, branch, aluop} <= {1'b1, 1'b1, 1'b1, 1'b1, 1'b0, 1'b0, 2'b00}; // Load
      7'b0100011 : {alusrc, memtoreg, regwrite, memread, memwrite, branch, aluop} <= {1'b1, 1'b0, 1'b0, 1'b0, 1'b1, 1'b0, 2'b00}; // Store
      7'b1100011 : {alusrc, memtoreg, regwrite, memread, memwrite, branch, aluop} <= {1'b0, 1'b0, 1'b0, 1'b0, 1'b0, 1'b1, 2'b11}; // Branch
      7'b1101111 : {alusrc, memtoreg, regwrite, memread, memwrite, branch, aluop} <= {1'b0, 1'b0, 1'b1, 1'b0, 1'b0, 1'b0, 2'b10}; // Jump
      7'b0110111 : {alusrc, memtoreg, regwrite, memread, memwrite, branch, aluop} <= {1'b0, 1'b0, 1'b1, 1'b0, 1'b0, 1'b0, 2'b10}; // LUI
      default    : {alusrc, memtoreg, regwrite, memread, memwrite, branch, aluop} <= {1'b0, 1'b0, 1'b0, 1'b0, 1'b0, 1'b0, 2'b00};
    endcase
  end

endmodule

riscv_matmul/riscv_matmul.srcs/sim_1/new/tb_main_control_unit.sv
`timescale 1ns / 1ps

module tb_main_control_unit();
  
  // Testbench signals
  reg [6:0] opcode;
  wire regwrite;
  wire memread;
  wire memwrite;
  wire memtoreg;
  wire alusrc;
  wire branch;
  wire [1:0] aluop;
  
  // Expected outputs storage
  reg exp_regwrite;
  reg exp_memread;
  reg exp_memwrite;
  reg exp_memtoreg;
  reg exp_alusrc;
  reg exp_branch;
  reg [1:0] exp_aluop;
  
  // Test control
  integer test_count = 0;
  integer pass_count = 0;
  integer fail_count = 0;
  reg test_pass;
  
  // Instantiate the module under test
  main_control_unit dut (
    .opcode(opcode),
    .regwrite(regwrite),
    .memread(memread),
    .memwrite(memwrite),
    .memtoreg(memtoreg),
    .alusrc(alusrc),
    .branch(branch),
    .aluop(aluop)
  );
  
  // Task to check outputs against expected values
  task check_outputs;
    input [6:0] opcode_input;
    input exp_regwrite, exp_memread, exp_memwrite, exp_memtoreg, exp_alusrc, exp_branch;
    input [1:0] exp_aluop;
    input string instruction_name;
    
    begin
      test_count = test_count + 1;
      test_pass = 1;
      
      // Apply opcode
      opcode = opcode_input;
      #10; // Wait for combinational logic to settle
      
      // Check each output
      if (regwrite !== exp_regwrite) begin
        $display("FAIL: %s (opcode: %7b) - regwrite: expected %b, got %b", 
                 instruction_name, opcode_input, exp_regwrite, regwrite);
        test_pass = 0;
      end
      
      if (memread !== exp_memread) begin
        $display("FAIL: %s (opcode: %7b) - memread: expected %b, got %b", 
                 instruction_name, opcode_input, exp_memread, memread);
        test_pass = 0;
      end
      
      if (memwrite !== exp_memwrite) begin
        $display("FAIL: %s (opcode: %7b) - memwrite: expected %b, got %b", 
                 instruction_name, opcode_input, exp_memwrite, memwrite);
        test_pass = 0;
      end
      
      if (memtoreg !== exp_memtoreg) begin
        $display("FAIL: %s (opcode: %7b) - memtoreg: expected %b, got %b", 
                 instruction_name, opcode_input, exp_memtoreg, memtoreg);
        test_pass = 0;
      end
      
      if (alusrc !== exp_alusrc) begin
        $display("FAIL: %s (opcode: %7b) - alusrc: expected %b, got %b", 
                 instruction_name, opcode_input, exp_alusrc, alusrc);
        test_pass = 0;
      end
      
      if (branch !== exp_branch) begin
        $display("FAIL: %s (opcode: %7b) - branch: expected %b, got %b", 
                 instruction_name, opcode_input, exp_branch, branch);
        test_pass = 0;
      end
      
      if (aluop !== exp_aluop) begin
        $display("FAIL: %s (opcode: %7b) - aluop: expected %b, got %b", 
                 instruction_name, opcode_input, exp_aluop, aluop);
        test_pass = 0;
      end
      
      if (test_pass) begin
        $display("PASS: %s (opcode: %7b) - All outputs match expected values", 
                 instruction_name, opcode_input);
        pass_count = pass_count + 1;
      end else begin
        fail_count = fail_count + 1;
      end
    end
  endtask
  
  // Initialize test
  initial begin
    $display("=========================================");
    $display("Starting testbench for main_control_unit");
    $display("=========================================\n");
    
    // Test 1: R-type instructions (7'b0110011)
    $display("Test 1: R-type instructions");
    check_outputs(7'b0110011, 1'b1, 1'b0, 1'b0, 1'b0, 1'b0, 1'b0, 2'b10, "R-type");
    
    // Test 2: I-type immediate instructions (7'b0010011)
    $display("\nTest 2: I-type immediate instructions");
    check_outputs(7'b0010011, 1'b1, 1'b0, 1'b0, 1'b0, 1'b1, 1'b0, 2'b10, "I-type");
    
    // Test 3: Load instructions (7'b0000011)
    $display("\nTest 3: Load instructions");
    check_outputs(7'b0000011, 1'b1, 1'b1, 1'b0, 1'b1, 1'b1, 1'b0, 2'b00, "Load");
    
    // Test 4: Store instructions (7'b0100011)
    $display("\nTest 4: Store instructions");
    check_outputs(7'b0100011, 1'b0, 1'b0, 1'b1, 1'b0, 1'b1, 1'b0, 2'b00, "Store");
    
    // Test 5: Branch instructions (7'b1100011)
    $display("\nTest 5: Branch instructions");
    check_outputs(7'b1100011, 1'b0, 1'b0, 1'b0, 1'b0, 1'b0, 1'b1, 2'b11, "Branch");
    
    // Test 6: Jump instructions (7'b1101111)
    $display("\nTest 6: Jump instructions");
    check_outputs(7'b1101111, 1'b1, 1'b0, 1'b0, 1'b0, 1'b0, 1'b0, 2'b10, "Jump");
    
    // Test 7: LUI instructions (7'b0110111)
    $display("\nTest 7: LUI instructions");
    check_outputs(7'b0110111, 1'b1, 1'b0, 1'b0, 1'b0, 1'b0, 1'b0, 2'b10, "LUI");
    
    // Test 8: Default case (undefined opcodes)
    $display("\nTest 8: Default/undefined opcodes");
    
    // Test multiple undefined opcodes
    check_outputs(7'b0000000, 1'b0, 1'b0, 1'b0, 1'b0, 1'b0, 1'b0, 2'b00, "Undefined 0000000");
    check_outputs(7'b1111111, 1'b0, 1'b0, 1'b0, 1'b0, 1'b0, 1'b0, 2'b00, "Undefined 1111111");
    check_outputs(7'b1010101, 1'b0, 1'b0, 1'b0, 1'b0, 1'b0, 1'b0, 2'b00, "Undefined 1010101");
    
    // Test 9: Additional edge cases (boundary values)
    $display("\nTest 9: Additional edge cases");
    check_outputs(7'b1110111, 1'b0, 1'b0, 1'b0, 1'b0, 1'b0, 1'b0, 2'b00, "Edge case 1");
    check_outputs(7'b0101010, 1'b0, 1'b0, 1'b0, 1'b0, 1'b0, 1'b0, 2'b00, "Edge case 2");
    
    // Test 10: Rapid opcode changes (stress test)
    $display("\nTest 10: Rapid opcode changes");
    for (integer i = 0; i < 5; i = i + 1) begin
      opcode = $random;
      #5; // Quick check without verbose output
    end
    
    // Final summary
    $display("\n=========================================");
    $display("Test Summary");
    $display("=========================================");
    $display("Total tests run: %0d", test_count);
    $display("Tests passed:    %0d", pass_count);
    $display("Tests failed:    %0d", fail_count);
    
    if (fail_count == 0) begin
      $display("\n✅ ALL TESTS PASSED!");
    end else begin
      $display("\n❌ SOME TESTS FAILED!");
    end
    
    $display("=========================================\n");
    
    // End simulation
    #10;
    $finish;
  end
  
  // Optional: Monitor to track all signal changes
  initial begin
    $monitor("Time: %0t | Opcode: %7b | Signals: {alusrc=%b, memtoreg=%b, regwrite=%b, memread=%b, memwrite=%b, branch=%b, aluop=%b}", 
             $time, opcode, alusrc, memtoreg, regwrite, memread, memwrite, branch, aluop);
  end
  
  // Generate waveform dump for visualization
  initial begin
    $dumpfile("main_control_unit.vcd");
    $dumpvars(0, tb_main_control_unit);
  end
  
endmodule

riscv_matmul/riscv_matmul.sim/sim_1/behav/xsim/main_control_unit.vcd
$date
   Mon Dec 29 23:31:00 2025
$end

$version
  2023.2
  $dumpfile ("main_control_unit.vcd") 
$end

$timescale
  1ps
$end

$scope module tb_main_control_unit $end
$var reg 7 ! opcode [6:0] $end
$var wire 1 " regwrite $end
$var wire 1 # memread $end
$var wire 1 $ memwrite $end
$var wire 1 % memtoreg $end
$var wire 1 & alusrc $end
$var wire 1 ' branch $end
$var wire 2 ( aluop [1:0] $end
$var reg 1 ) exp_regwrite $end
$var reg 1 * exp_memread $end
$var reg 1 + exp_memwrite $end
$var reg 1 , exp_memtoreg $end
$var reg 1 - exp_alusrc $end
$var reg 1 . exp_branch $end
$var reg 2 / exp_aluop [1:0] $end
$var integer 32 0 test_count [31:0] $end
$var integer 32 1 pass_count [31:0] $end
$var integer 32 2 fail_count [31:0] $end
$var reg 1 3 test_pass $end
$scope module dut $end
$var wire 7 4 opcode [6:0] $end
$var reg 1 5 regwrite $end
$var reg 1 6 memread $end
$var reg 1 7 memwrite $end
$var reg 1 8 memtoreg $end
$var reg 1 9 alusrc $end
$var reg 1 : branch $end
$var reg 2 ; aluop [1:0] $end
$upscope $end
$scope begin Block159_2 $end
$var integer 32 < i [31:0] $end
$upscope $end
$scope task check_outputs $end
$var reg 7 = opcode_input [6:0] $end
$var reg 1 > exp_regwrite $end
$var reg 1 ? exp_memread $end
$var reg 1 @ exp_memwrite $end
$var reg 1 A exp_memtoreg $end
$var reg 1 B exp_alusrc $end
$var reg 1 C exp_branch $end
$var reg 2 D exp_aluop [1:0] $end
$upscope $end
$upscope $end
$enddefinitions $end

#0
$dumpvars
b110011 !
1"
0#
0$
0%
0&
0'
b10 (
x)
x*
x+
x,
x-
x.
bx /
b1 0
b0 1
b0 2
13
b110011 4
15
06
07
08
09
0:
b10 ;
bx <
b110011 =
1>
0?
0@
0A
0B
0C
b10 D
$end

#10000
b10011 !
1&
b10 0
b1 1
b10011 4
19
b10011 =
1B

#20000
b11 !
1#
1%
b0 (
b11 0
b10 1
b11 4
16
18
b0 ;
b11 =
1?
1A
b0 D

#30000
b100011 !
0"
0#
1$
0%
b100 0
b11 1
b100011 4
05
06
17
08
b100011 =
0>
0?
1@
0A

#40000
b1100011 !
0$
0&
1'
b11 (
b101 0
b100 1
b1100011 4
07
09
1:
b11 ;
b1100011 =
0@
0B
1C
b11 D

#50000
b1101111 !
1"
0'
b10 (
b110 0
b101 1
b1101111 4
15
0:
b10 ;
b1101111 =
1>
0C
b10 D

#60000
b110111 !
b111 0
b110 1
b110111 4
b110111 =

#70000
b0 !
0"
b0 (
b1000 0
b111 1
b0 4
05
b0 ;
b0 =
0>
b0 D

#80000
b1111111 !
b1001 0
b1000 1
b1111111 4
b1111111 =

#90000
b1010101 !
b1010 0
b1001 1
b1010101 4
b1010101 =

#100000
b1110111 !
b1011 0
b1010 1
b1110111 4
b1110111 =

#110000
b101010 !
b1100 0
b1011 1
b101010 4
b101010 =

#120000
b100100 !
b1100 1
b100100 4
b0 <

#125000
b1 !
b1 4
b1 <

#130000
b1001 !
b1001 4
b10 <

#135000
b1100011 !
1'
b11 (
b1100011 4
1:
b11 ;
b11 <

#140000
b1101 !
0'
b0 (
b1101 4
0:
b0 ;
b100 <

#145000
b101 <
